aiogram_lazy_kb/__init__.py
aiogram_lazy_kb/factory.py
aiogram_lazy_kb-0.1.0.dist-info/METADATA
aiogram_lazy_kb-0.1.0.dist-info/WHEEL
aiogram_lazy_kb-0.1.0.dist-info/licenses/LICENSE
aiogram_lazy_kb-0.1.0.dist-info/RECORD
