Metadata-Version: 2.4
Name: aiogram-lazy-kb
Version: 0.1.0
Summary: Простой генератор клавиатур для aiogram 3.x
Project-URL: Homepage, https://github.com/твой_гитхаб/aiogram-lazy-kb
Author-email: iQOOZ10FUN2026 <vova.egor.j@gmail.com>
License-File: LICENSE
Classifier: License :: OSI Approved :: MIT License
Classifier: Operating System :: OS Independent
Classifier: Programming Language :: Python :: 3
Requires-Python: >=3.9
Requires-Dist: aiogram>=3.0.0
